{
  "info": {
    "_postman_id": "3f8f796b-1db8-4cd6-8e7a-6e38c92e6682",
    "name": "06.User Update Booking",
    "schema": "https://schema.getpostman.com/json/collection/v2.1.0/collection.json",
    "_exporter_id": "52483416"
  },
  "item": [
    {
      "name": "Update Booking",
      "event": [
        {
          "listen": "test",
          "script": {
            "exec": [
              "pm.test(\"Status code is 200\", function () {\r",
              "    pm.response.to.have.status(200);\r",
              "});"
            ],
            "type": "text/javascript",
            "packages": {},
            "requests": {}
          }
        }
      ],
      "request": {
        "auth": {
          "type": "bearer",
          "bearer": [
            {
              "key": "token",
              "value": "{{TOKEN}}",
              "type": "string"
            }
          ]
        },
        "method": "PUT",
        "header": [],
        "body": {
          "mode": "raw",
          "raw": "{\r\n    \"rentalDate\": \"{{$randomDateRecent}}\"\r\n}",
          "options": {
            "raw": {
              "language": "json"
            }
          }
        },
        "url": {
          "raw": "{{url}}/api/v1/bookings/69a5aa1e584f0b09ae67321d",
          "host": [
            "{{url}}"
          ],
          "path": [
            "api",
            "v1",
            "bookings",
            "69a5aa1e584f0b09ae67321d"
          ]
        }
      },
      "response": []
    }
  ]
}